aioinfluxdb/__init__.py
aioinfluxdb/aiohttp_client.py
aioinfluxdb/client.py
aioinfluxdb/constants.py
aioinfluxdb/csv_parser.py
aioinfluxdb/exceptions.py
aioinfluxdb/flux_table.py
aioinfluxdb/py.typed
aioinfluxdb/serializer.py
aioinfluxdb/types.py
aioinfluxdb-0.2.0.dist-info/LICENSE
aioinfluxdb-0.2.0.dist-info/WHEEL
aioinfluxdb-0.2.0.dist-info/METADATA
aioinfluxdb-0.2.0.dist-info/RECORD
