Metadata-Version: 2.1
Name: aioinfluxdb
Version: 0.2.0
Summary: InfluxDB v2 Python SDK with asyncio support
License: MIT
Keywords: influxdb,influx,asyncio,sdk,v2
Author: Byeonghoon Yoo
Author-email: bh322yoo@gmail.com
Requires-Python: >=3.7,<4.0
Classifier: Development Status :: 2 - Pre-Alpha
Classifier: Environment :: Web Environment
Classifier: Framework :: AsyncIO
Classifier: Framework :: aiohttp
Classifier: Intended Audience :: Developers
Classifier: License :: OSI Approved :: MIT License
Classifier: Natural Language :: English
Classifier: Operating System :: OS Independent
Classifier: Programming Language :: Python :: 3
Classifier: Programming Language :: Python :: 3 :: Only
Classifier: Programming Language :: Python :: 3.10
Classifier: Programming Language :: Python :: 3.7
Classifier: Programming Language :: Python :: 3.8
Classifier: Programming Language :: Python :: 3.9
Classifier: Programming Language :: Python :: Implementation
Classifier: Programming Language :: Python :: Implementation :: CPython
Classifier: Programming Language :: Python :: Implementation :: PyPy
Classifier: Topic :: Database
Classifier: Topic :: Database :: Front-Ends
Classifier: Topic :: Internet
Classifier: Topic :: Software Development :: Libraries
Classifier: Topic :: Software Development :: Libraries :: Python Modules
Classifier: Typing :: Typed
Provides-Extra: pandas
Requires-Dist: aiocsv (>=1.2.1,<2.0.0)
Requires-Dist: aiohttp[speedups] (>=3.8.1,<4.0.0)
Requires-Dist: ciso8601 (>=2.2.0,<3.0.0)
Requires-Dist: isal (>=0.11.1,<0.12.0)
Requires-Dist: orjson (>=3.6.6,<4.0.0)
Requires-Dist: pandas (>=1.4.0,<2.0.0); (python_version >= "3.8" and python_version < "4.0") and (extra == "pandas")
Requires-Dist: typing-extensions (>=4.0.1,<5.0.0)
